<?xml version="1.0" encoding="utf-8" ?>
<dwsync>
<file name="index.html" server="D:/wamp/www/" local="129872347498750000" remote="129872347490000000" />
<file name="about.html" server="D:/wamp/www/" local="129872260368593750" remote="129872260360000000" />
<file name="law.html" server="D:/wamp/www/" local="129872349520468750" remote="129872349520000000" />
<file name="news.html" server="D:/wamp/www/" local="129872349520000000" remote="129872349520000000" />
<file name="perfor.html" server="D:/wamp/www/" local="129872349307812500" remote="129872349300000000" />
<file name="message.html" server="D:/wamp/www/" local="129872352457343750" remote="129872352450000000" />
<file name="show.html" server="D:/wamp/www/" local="129873073230156250" remote="129873073230000000" />
<file name="department.html" server="D:/wamp/www/" local="129873142380312500" remote="129873142380000000" />
<file name="msg_view.html" server="D:/wamp/www/" local="129872346625625000" remote="129872346620000000" />
<file name="yinyueren.html" server="D:/wamp/www/" local="129872400482500000" remote="129872400480000000" />
<file name="display.html" server="D:/wamp/www/" local="129872370366250000" remote="129872370360000000" />
<file name="slide.html" server="D:/wamp/www/" local="129877576550000000" remote="129877576550000000" />
</dwsync>