<?xml version="1.0" encoding="utf-8" ?>
<dwsync>
<file name="index.html" server="D:/wamp/www/" local="129901860093437500" remote="129901860090000000" />
<file name="news_show.html" server="D:/wamp/www/" local="129903381011875000" remote="129903381010000000" />
<file name="about.html" server="D:/wamp/www/" local="129903431535781250" remote="129903431530000000" />
<file name="activity_show.html" server="D:/wamp/www/" local="129903546369843750" remote="129903546360000000" />
<file name="contact.html" server="D:/wamp/www/" local="129903435111562500" remote="129903435110000000" />
<file name="feedback.html" server="D:/wamp/www/" local="129903542637500000" remote="129903542630000000" />
<file name="case.html" server="D:/wamp/www/" local="129903451063593750" remote="129903451060000000" />
<file name="service.html" server="D:/wamp/www/" local="129903467897656250" remote="129903467890000000" />
<file name="activity.html" server="D:/wamp/www/" local="129903493976562500" remote="129903493970000000" />
<file name="dress.html" server="D:/wamp/www/" local="129903563577187500" remote="129903563570000000" />
<file name="dress_make.html" server="D:/wamp/www/" local="129905175741875000" remote="129905175740000000" />
</dwsync>