<?xml version="1.0" encoding="utf-8" ?>
<dwsync>
<file name="bg.gif" server="D:/wamp/www/" local="129866424332968750" remote="129866424330000000" />
<file name="top_flash.gif" server="D:/wamp/www/" local="129866430729218750" remote="129866430720000000" />
<file name="nav_bg.gif" server="D:/wamp/www/" local="129867028970937500" remote="129867028970000000" />
<file name="nav_menu.gif" server="D:/wamp/www/" local="129867026852500000" remote="129867026850000000" />
<file name="nav_menu_hover.gif" server="D:/wamp/www/" local="129867026135625000" remote="129867026130000000" />
<file name="slide_img.gif" server="D:/wamp/www/" local="129867033888593750" remote="129867033880000000" />
<file name="contact_bg.gif" server="D:/wamp/www/" local="129867037516406250" remote="129867037510000000" />
<file name="qq_icos.gif" server="D:/wamp/www/" local="129867053076093750" remote="129867053070000000" />
<file name="address_ico.gif" server="D:/wamp/www/" local="129867053845156250" remote="129867053840000000" />
<file name="link_tit.gif" server="D:/wamp/www/" local="129867099104687500" remote="129867099100000000" />
<file name="link_foot_bg.gif" server="D:/wamp/www/" local="129867099228906250" remote="129867099220000000" />
<file name="case_tit_bg.gif" server="D:/wamp/www/" local="129867122353906250" remote="129867122350000000" />
<file name="case_tit_ico.gif" server="D:/wamp/www/" local="129867187853906250" remote="129867187850000000" />
<file name="hang_more_btn.gif" server="D:/wamp/www/" local="129867189976250000" remote="129867189970000000" />
<file name="case_fill_bg.png" server="D:/wamp/www/" local="129867192676250000" remote="129867192670000000" />
<file name="case_foot_bg.gif" server="D:/wamp/www/" local="129867181704687500" remote="129867181700000000" />
<file name="hotel_tit_ico.gif" server="D:/wamp/www/" local="129867196247812500" remote="129867196240000000" />
<file name="turn_btn.gif" server="D:/wamp/www/" local="129867202058750000" remote="129867202050000000" />
<file name="case_content_bg.gif" server="D:/wamp/www/" local="129867199025000000" remote="129867199020000000" />
<file name="more_btn.gif" server="D:/wamp/www/" local="129867213933125000" remote="129867213930000000" />
<file name="case_img.gif" server="D:/wamp/www/" local="129867218898906250" remote="129867218890000000" />
<file name="case_img_bg.gif" server="D:/wamp/www/" local="129867223020781250" remote="129867223020000000" />
<file name="case_bottom_tit_bg.gif" server="D:/wamp/www/" local="129867228065468750" remote="129867228060000000" />
<file name="hotel_img_bg.gif" server="D:/wamp/www/" local="129867234783281250" remote="129867234780000000" />
<file name="detail_btn.gif" server="D:/wamp/www/" local="129867245055468750" remote="129867245050000000" />
<file name="news_wrap_bg.gif" server="D:/wamp/www/" local="129867259746406250" remote="129867259740000000" />
<file name="news_tit_bg.gif" server="D:/wamp/www/" local="129867261707031250" remote="129867261700000000" />
<file name="news_tit_ico.gif" server="D:/wamp/www/" local="129867266517031250" remote="129867266510000000" />
<file name="more_ico.gif" server="D:/wamp/www/" local="129867270447343750" remote="129867270440000000" />
<file name="new_foot_bg.gif" server="D:/wamp/www/" local="129867255848593750" remote="129867255840000000" />
<file name="hotel_img.gif" server="D:/wamp/www/" local="129867233965625000" remote="129867233960000000" />
<file name="gallery_tit_ico.gif" server="D:/wamp/www/" local="129867279291093750" remote="129867279290000000" />
<file name="gallery_pic.gif" server="D:/wamp/www/" local="129868745525468750" remote="129868745520000000" />
<file name="prev_btn.gif" server="D:/wamp/www/" local="129868743569375000" remote="129868743560000000" />
<file name="next_ico.gif" server="D:/wamp/www/" local="129868743479218750" remote="129868743470000000" />
<file name="class_wrap_bg.gif" server="D:/wamp/www/" local="129868760280312500" remote="129868760280000000" />
<file name="class_foot_bg.gif" server="D:/wamp/www/" local="129868758129843750" remote="129868758120000000" />
<file name="class_tit_ico.gif" server="D:/wamp/www/" local="129868766178125000" remote="129868766170000000" />
<file name="class_img_bg.png" server="D:/wamp/www/" local="129868770234375000" remote="129868770230000000" />
<file name="class_img.png" server="D:/wamp/www/" local="129868772104218750" remote="129868772100000000" />
<file name="recomend_tit_bg.gif" server="D:/wamp/www/" local="129868795600156250" remote="129868795600000000" />
<file name="recomend_pic.gif" server="D:/wamp/www/" local="129868802525312500" remote="129868802520000000" />
<file name="sub_tit_bg.gif" server="D:/wamp/www/" local="129868836722187500" remote="129868836720000000" />
<file name="sub_tit_4.gif" server="D:/wamp/www/" local="129868842852500000" remote="129868842850000000" />
<file name="wrap_bg.gif" server="D:/wamp/www/" local="129868834200468750" remote="129868834200000000" />
<file name="sub_nav_bg.gif" server="D:/wamp/www/" local="129868847504687500" remote="129868847500000000" />
<file name="sub_dynamic_news.gif" server="D:/wamp/www/" local="129868881240000000" remote="129868881240000000" />
<file name="sub_contact_tit.gif" server="D:/wamp/www/" local="129868886427812500" remote="129868886420000000" />
<file name="contact_qq.gif" server="D:/wamp/www/" local="129868895644843750" remote="129868895640000000" />
<file name="sub_tit_6.gif" server="D:/wamp/www/" local="129868915687812500" remote="129868915680000000" />
<file name="map.gif" server="D:/wamp/www/" local="129868918425625000" remote="129868918420000000" />
<file name="sub_tit_2.gif" server="D:/wamp/www/" local="129868940980468750" remote="129868940980000000" />
<file name="class_list_ico.gif" server="D:/wamp/www/" local="129868928012031250" remote="129868928010000000" />
<file name="sub_tit_3.gif" server="D:/wamp/www/" local="129868958442031250" remote="129868958440000000" />
<file name="tit_after_bg.gif" server="D:/wamp/www/" local="129868964534062500" remote="129868964530000000" />
<file name="faq_bg.gif" server="D:/wamp/www/" local="129868990265468750" remote="129868990260000000" />
<file name="msg_sub_btn.gif" server="D:/wamp/www/" local="129869010493906250" remote="129869010490000000" />
<file name="sub_gallery.gif" server="D:/wamp/www/" local="129868972567968750" remote="129868972560000000" />
<file name="package_img.gif" server="D:/wamp/www/" local="129869015968437500" remote="129869015960000000" />
<file name="hotel_img_wrap.gif" server="D:/wamp/www/" local="129869029955625000" remote="129869029950000000" />
<file name="sub_tit_5.gif" server="D:/wamp/www/" local="129869041391093750" remote="129869041390000000" />
<file name="sub_case_img.gif" server="D:/wamp/www/" local="129869047167500000" remote="129869047160000000" />
<file name="case_bg.gif" server="D:/wamp/www/" local="129869045297656250" remote="129869045290000000" />
<file name="sub_tit_1.gif" server="D:/wamp/www/" local="129869076389687500" remote="129869076380000000" />
<file name="heart_ico.png" server="D:/wamp/www/" local="129869093877500000" remote="129869093870000000" />
<file name="gallery_up.gif" server="D:/wamp/www/" local="129870476319218750" remote="129870476310000000" />
<file name="gallery_down.gif" server="D:/wamp/www/" local="129870483695937500" remote="129870483690000000" />
<file name="sub_gallery_img.gif" server="D:/wamp/www/" local="129870473497968750" remote="129870473490000000" />
<file name="big_img.gif" server="D:/wamp/www/" local="129870484330312500" remote="129870484330000000" />
</dwsync>